{
    "Objects": [
        {
            "name": "Land_Airfield_Hangar_Green",
            "pos": [
                12151.0849609375,
                146.6436309814453,
                12547.3037109375
            ],
            "ypr": [
                21.481246948242189,
                -0.0,
                -0.0
            ]
        },
        {
            "name": "Land_Airfield_Hangar_Green",
            "pos": [
                12192.2216796875,
                146.8551025390625,
                12531.0859375
            ],
            "ypr": [
                21.481246948242189,
                -0.0,
                -0.0
            ]
        },
        {
            "name": "Land_Airfield_Hangar_Green",
            "pos": [
                12110.291015625,
                146.77352905273438,
                12564.0283203125
            ],
            "ypr": [
                21.481246948242189,
                -0.0,
                -0.0
            ]
        },
        {
            "name": "Land_Wreck_C130J",
            "pos": [
                12239.990234375,
                145.88716735839845,
                12469.603515625
            ],
            "ypr": [
                -62.80187225341797,
                -0.0,
                -0.0
            ]
        },
        {
            "name": "Land_Tisy_RadarB_Base",
            "pos": [
                11999.0,
                139.9550018310547,
                12501.099609375
            ],
            "ypr": [
                -158.68199157714845,
                0.0,
                0.0
            ]
        },
        {
            "name": "Land_Tisy_RadarB_Antenna",
            "pos": [
                11986.7998046875,
                139.9949951171875,
                12501.0
            ],
            "ypr": [
                -75.99999237060547,
                0.0,
                0.0
            ]
        },
        {
            "name": "Land_Mil_AircraftShelter",
            "pos": [
                11845.98828125,
                140.86814880371095,
                12629.2919921875
            ],
            "ypr": [
                -69.40221405029297,
                -0.0,
                -0.0
            ]
        },
        {
            "name": "Land_Tisy_HQ",
            "pos": [
                11970.5,
                144.10000610351563,
                12622.7998046875
            ],
            "ypr": [
                76.98789978027344,
                0.0,
                0.0
            ]
        },
        {
            "name": "Land_Mil_ATC_Small",
            "pos": [
                12022.0224609375,
                150.61241149902345,
                12527.0078125
            ],
            "ypr": [
                -153.4873809814453,
                -0.0,
                -0.0
            ]
        },
        {
            "name": "Land_Mil_Barracks5",
            "pos": [
                12118.796875,
                145.86865234375,
                12460.326171875
            ],
            "ypr": [
                20.726577758789064,
                -0.0,
                -0.0
            ]
        },
        {
            "name": "Land_Mil_Barracks6",
            "pos": [
                12083.36328125,
                140.5223388671875,
                12472.5810546875
            ],
            "ypr": [
                -155.7063446044922,
                -0.0,
                -0.0
            ]
        },
        {
            "name": "Land_Tisy_Barracks",
            "pos": [
                12206.689453125,
                144.51577758789063,
                12659.150390625
            ],
            "ypr": [
                23.366430282592775,
                -0.0,
                -0.0
            ]
        },
        {
            "name": "Land_Tisy_KitchenRoom",
            "pos": [
                12160.0,
                144.89999389648438,
                12683.2001953125
            ],
            "ypr": [
                114.30499267578125,
                0.0,
                0.0
            ]
        }
    ]
}